idem_core_functions/conf.py
idem_core_functions/version.py
idem_core_functions/exec/core/collection.py
idem_core_functions/exec/core/conversion.py
idem_core_functions/exec/core/encoding.py
idem_core_functions/exec/core/string.py
idem_core_functions/exec/core/encoder/base64.py
idem_core_functions/exec/core/encryption/gpg.py
idem_core_functions-2.0.0.dist-info/LICENSE
idem_core_functions-2.0.0.dist-info/METADATA
idem_core_functions-2.0.0.dist-info/WHEEL
idem_core_functions-2.0.0.dist-info/entry_points.txt
idem_core_functions-2.0.0.dist-info/top_level.txt
idem_core_functions-2.0.0.dist-info/RECORD
